pyutil/__init__.py
pyutil/data_structures.py
pyutil/files.py
pyutil/general.py
pyutil/haskell.py
pyutil/math.py
python_util-1.2.1.dist-info/LICENSE
python_util-1.2.1.dist-info/METADATA
python_util-1.2.1.dist-info/WHEEL
python_util-1.2.1.dist-info/top_level.txt
python_util-1.2.1.dist-info/RECORD
