Metadata-Version: 2.1
Name: python-util
Version: 1.2.1
Summary: A small python utilities addon
Home-page: https://github.com/MisterL2/python-util
Author: MisterL2
Author-email: misterl2@gmx.net
License: UNKNOWN
Platform: UNKNOWN
Classifier: Development Status :: 4 - Beta
Classifier: Programming Language :: Python :: 3
Classifier: Programming Language :: Python :: 3.6
Classifier: License :: OSI Approved :: MIT License
Classifier: Operating System :: OS Independent
